pfutil.cpython-310-darwin.so
pfutil-1.0.3.dist-info/COPYING
pfutil-1.0.3.dist-info/METADATA
pfutil-1.0.3.dist-info/WHEEL
pfutil-1.0.3.dist-info/top_level.txt
pfutil-1.0.3.dist-info/RECORD
