Metadata-Version: 2.1
Name: pfutil
Version: 1.0.3
Summary: Fast and Redis-compatible HyperLogLog extension for Python 3
Home-page: https://github.com/danchen6/pfutil
Author: Dan Chen
Author-email: danchen666666@gmail.com
License: 3-Clause BSD License
Platform: UNKNOWN
Classifier: Development Status :: 4 - Beta
Classifier: Intended Audience :: Developers
Classifier: License :: OSI Approved :: BSD License
Classifier: Programming Language :: C
Classifier: Programming Language :: Python :: 3
Classifier: Topic :: Database
Classifier: Topic :: Scientific/Engineering
License-File: COPYING
